clustered_imputation/__init__.py
clustered_imputation/getClusters.py
clustered_imputation/main.py
clustered_imputation/basicImputer/__init__.py
clustered_imputation/basicImputer/em.py
clustered_imputation/basicImputer/mice.py
clustered_imputation/basicImputer/sice.py
clustered_imputation/clusterBase/__init__.py
clustered_imputation/clusterBase/clustering.py
clustered_imputation/clusterBase/ohe.py
clustered_imputation/dummyData/__init__.py
clustered_imputation/dummyData/dataCreation.py
clustered_imputation-1.0.2.dist-info/LICENSE
clustered_imputation-1.0.2.dist-info/METADATA
clustered_imputation-1.0.2.dist-info/WHEEL
clustered_imputation-1.0.2.dist-info/top_level.txt
clustered_imputation-1.0.2.dist-info/RECORD
