Metadata-Version: 2.1
Name: clustered-imputation
Version: 1.0.2
Summary: Adding correlation to handle MNAR
Author: MRINAL KANGSA BANIK
Author-email: <manukbanik30@gmail.com>
Keywords: python,imputation,MNAR
Classifier: Development Status :: 1 - Planning
Classifier: Intended Audience :: Developers
Classifier: Programming Language :: Python :: 3
Classifier: Operating System :: Unix
Classifier: Operating System :: MacOS :: MacOS X
Classifier: Operating System :: Microsoft :: Windows
License-File: LICENSE
Requires-Dist: numpy
Requires-Dist: pandas
Requires-Dist: scikit-learn
Requires-Dist: fancyimpute
